{
  "version": "1",
  "cognitoConfig": {
    "identityPoolName": "adsfebada5c03_identitypool_bada5c03",
    "allowUnauthenticatedIdentities": false,
    "resourceNameTruncated": "adsfebada5c03",
    "userPoolName": "adsfebada5c03_userpool_bada5c03",
    "autoVerifiedAttributes": [
      "email"
    ],
    "mfaConfiguration": "OFF",
    "mfaTypes": [
      "SMS Text Message"
    ],
    "smsAuthenticationMessage": "Your authentication code is {####}",
    "smsVerificationMessage": "Your verification code is {####}",
    "emailVerificationSubject": "Your verification code",
    "emailVerificationMessage": "Your verification code is {####}",
    "defaultPasswordPolicy": false,
    "passwordPolicyMinLength": 8,
    "passwordPolicyCharacters": [],
    "requiredAttributes": [
      "email"
    ],
    "aliasAttributes": [],
    "userpoolClientGenerateSecret": false,
    "userpoolClientRefreshTokenValidity": 30,
    "userpoolClientWriteAttributes": [
      "email"
    ],
    "userpoolClientReadAttributes": [
      "email"
    ],
    "userpoolClientLambdaRole": "adsfebbada5c03_userpoolclient_lambda_role",
    "userpoolClientSetAttributes": false,
    "sharedId": "bada5c03",
    "resourceName": "adsfebada5c03",
    "authSelections": "identityPoolAndUserPool",
    "useDefault": "defaultSocial",
    "hostedUI": true,
    "hostedUIDomainName": "adsfebada5c03-bada5c03",
    "authProvidersUserPool": [],
    "hostedUIProviderMeta": "[]",
    "oAuthMetadata": "{\"AllowedOAuthFlows\":[\"code\"],\"AllowedOAuthScopes\":[\"phone\",\"email\",\"openid\",\"profile\",\"aws.cognito.signin.user.admin\"],\"CallbackURLs\":[\"adsphere://\"],\"LogoutURLs\":[\"adsphere://\"]}",
    "userPoolGroupList": [],
    "serviceName": "Cognito",
    "usernameCaseSensitive": false,
    "useEnabledMfas": true
  }
}